watchlogs/__init__.py
watchlogs/watchlogs.py
watchlogs-0.1.3.21.dist-info/LICENSE.md
watchlogs-0.1.3.21.dist-info/METADATA
watchlogs-0.1.3.21.dist-info/WHEEL
watchlogs-0.1.3.21.dist-info/entry_points.txt
watchlogs-0.1.3.21.dist-info/top_level.txt
watchlogs-0.1.3.21.dist-info/RECORD
