Metadata-Version: 2.1
Name: watchlogs
Version: 0.1.3.21
Summary: A simple, colourful logfile watcher
Home-page: https://github.com/albanie/watchlogs
Author: Samuel Albanie
License: UNKNOWN
Platform: UNKNOWN
Classifier: Programming Language :: Python :: 3.6
Classifier: License :: OSI Approved :: MIT License
Classifier: Operating System :: POSIX :: Linux
Requires-Python: >=3.6
Requires-Dist: colored
Requires-Dist: seaborn
Requires-Dist: tailf
Requires-Dist: psutil
Requires-Dist: humanize
Requires-Dist: typeguard
